linus/.DS_Store
linus/__init__.py
linus-0.0.0.dist-info/LICENSE.txt
linus-0.0.0.dist-info/METADATA
linus-0.0.0.dist-info/WHEEL
linus-0.0.0.dist-info/RECORD
