Metadata-Version: 2.3
Name: linus
Version: 0.0.0
Summary: linus
License: Apache 2.0
Author: Felix Faltings
Author-email: faltings@csail.mit.edu
Requires-Python: >=3.12,<3.13
Classifier: License :: Other/Proprietary License
Classifier: Programming Language :: Python :: 3
Classifier: Programming Language :: Python :: 3.12
Project-URL: Repository, https://github.com/pgmikhael/linus
